{
  "upload_id": 19,
  "cache_key": "ed9b1decae4e4aa4e2d0044d4b47b78c6427372041c7d3adf4fb89271c2e1624_vision-v2.0",
  "extractor_version": "vision-v2.0",
  "status": "success",
  "flags": [],
  "statements": {
    "income_statement": {
      "statement_type": "income_statement",
      "currency": "KD",
      "unit_scale": 1,
      "periods": [
        {
          "label": "2024-12-31",
          "col_name": "2024"
        },
        {
          "label": "2023-12-31",
          "col_name": "2023"
        }
      ],
      "items": [
        {
          "label_raw": "Real estate rental income",
          "key": "real_estate_rental_income",
          "values": {
            "2024-12-31": 33497636.0,
            "2023-12-31": 28650658.0
          },
          "is_total": false
        },
        {
          "label_raw": "Revenue from contracts with customers",
          "key": "revenue_from_contracts_with_customers",
          "values": {
            "2024-12-31": 1424888.0,
            "2023-12-31": 249712.0
          },
          "is_total": false
        },
        {
          "label_raw": "34,862,514",
          "key": "total_revenue",
          "values": {
            "2024-12-31": 34862514.0,
            "2023-12-31": 28900570.0
          },
          "is_total": true
        },
        {
          "label_raw": "Real estate operating expenses",
          "key": "real_estate_operating_expenses",
          "values": {
            "2024-12-31": -9833924.0,
            "2023-12-31": -7069476.0
          },
          "is_total": false
        },
        {
          "label_raw": "Cost of contracts with customers",
          "key": "cost_of_contracts_with_customers",
          "values": {
            "2024-12-31": -2435987.0,
            "2023-12-31": -1115781.0
          },
          "is_total": false
        },
        {
          "label_raw": "12,269,911",
          "key": "total_real_estate_operating_expenses_and_cost_of_contracts_with_customers",
          "values": {
            "2024-12-31": -12269911.0,
            "2023-12-31": -8185257.0
          },
          "is_total": true
        },
        {
          "label_raw": "Gross income",
          "key": "gross_income",
          "values": {
            "2024-12-31": 22592603.0,
            "2023-12-31": 20715313.0
          },
          "is_total": true
        },
        {
          "label_raw": "Change in fair value of investment properties",
          "key": "change_in_fair_value_of_investment_properties",
          "values": {
            "2024-12-31": 9475562.0,
            "2023-12-31": -8070963.0
          },
          "is_total": false
        },
        {
          "label_raw": "Gain on sale of investment properties",
          "key": "gain_on_sale_of_investment_properties",
          "values": {
            "2024-12-31": null,
            "2023-12-31": 1958893.0
          },
          "is_total": false
        },
        {
          "label_raw": "Change in fair value of properties under development",
          "key": "change_in_fair_value_of_properties_under_development",
          "values": {
            "2024-12-31": 55683.0,
            "2023-12-31": 45790.0
          },
          "is_total": false
        },
        {
          "label_raw": "Change in fair value of financial assets at FVTPL",
          "key": "change_in_fair_value_of_financial_assets_at_fvtpl",
          "values": {
            "2024-12-31": 2485385.0,
            "2023-12-31": -758835.0
          },
          "is_total": false
        },
        {
          "label_raw": "Loss on sale of financial assets at FVTPL",
          "key": "loss_on_sale_of_financial_assets_at_fvtpl",
          "values": {
            "2024-12-31": -1739.0,
            "2023-12-31": -28233.0
          },
          "is_total": false
        },
        {
          "label_raw": "Dividend income",
          "key": "dividend_income",
          "values": {
            "2024-12-31": 375626.0,
            "2023-12-31": 362354.0
          },
          "is_total": false
        },
        {
          "label_raw": "Share of results of associates",
          "key": "share_of_results_of_associates",
          "values": {
            "2024-12-31": -2029236.0,
            "2023-12-31": 398441.0
          },
          "is_total": false
        },
        {
          "label_raw": "Loss on disposal of associate",
          "key": "loss_on_disposal_of_associate",
          "values": {
            "2024-12-31": null,
            "2023-12-31": -120000.0
          },
          "is_total": false
        },
        {
          "label_raw": "Other income",
          "key": "other_income",
          "values": {
            "2024-12-31": 490096.0,
            "2023-12-31": 391491.0
          },
          "is_total": false
        },
        {
          "label_raw": "33,370,980",
          "key": "total_gross_income_and_other_income",
          "values": {
            "2024-12-31": 33370980.0,
            "2023-12-31": 26995265.0
          },
          "is_total": true
        },
        {
          "label_raw": "General and administrative expenses",
          "key": "general_and_administrative_expenses",
          "values": {
            "2024-12-31": -3499309.0,
            "2023-12-31": -2967673.0
          },
          "is_total": false
        },
        {
          "label_raw": "Finance costs",
          "key": "finance_costs",
          "values": {
            "2024-12-31": -12890139.0,
            "2023-12-31": -10924254.0
          },
          "is_total": false
        },
        {
          "label_raw": "Provision charge for doubtful debts",
          "key": "provision_charge_for_doubtful_debts",
          "values": {
            "2024-12-31": null,
            "2023-12-31": -150927.0
          },
          "is_total": false
        },
        {
          "label_raw": "16,389,448",
          "key": "total_expenses_and_other_charges",
          "values": {
            "2024-12-31": -16389448.0,
            "2023-12-31": -14042853.0
          },
          "is_total": true
        },
        {
          "label_raw": "Profit for the year before taxation on overseas subsidiaries",
          "key": "profit_for_the_year_before_taxation_on_overseas_subsidiaries",
          "values": {
            "2024-12-31": 16981532.0,
            "2023-12-31": 12952412.0
          },
          "is_total": true
        },
        {
          "label_raw": "Taxation on overseas subsidiaries",
          "key": "taxation_on_overseas_subsidiaries",
          "values": {
            "2024-12-31": -692087.0,
            "2023-12-31": null
          },
          "is_total": false
        },
        {
          "label_raw": "Profit for the year before provisions for contribution to Kuwait Foundation for the Advancement of Sciences (KFAS), National Labour Support Tax (NLST), Zakat and directors' remuneration",
          "key": "profit_for_the_year_before_provisions_for_contribution_to_kfas_nlst_zakat_and_directors_remuneration",
          "values": {
            "2024-12-31": 16289445.0,
            "2023-12-31": 12952412.0
          },
          "is_total": true
        },
        {
          "label_raw": "Provision for KFAS, NLST and Zakat",
          "key": "provision_for_kfas_nlst_and_zakat",
          "values": {
            "2024-12-31": -744328.0,
            "2023-12-31": -633681.0
          },
          "is_total": false
        },
        {
          "label_raw": "Board of directors' remuneration",
          "key": "board_of_directors_remuneration",
          "values": {
            "2024-12-31": -60000.0,
            "2023-12-31": -60000.0
          },
          "is_total": false
        },
        {
          "label_raw": "Profit for the year",
          "key": "profit_for_the_year",
          "values": {
            "2024-12-31": 15485117.0,
            "2023-12-31": 12258751.0
          },
          "is_total": true
        },
        {
          "label_raw": "Owners of the Parent Company",
          "key": "owners_of_the_parent_company",
          "values": {
            "2024-12-31": 13414640.0,
            "2023-12-31": 11287000.0
          },
          "is_total": false
        },
        {
          "label_raw": "Non-controlling interests",
          "key": "non_controlling_interests",
          "values": {
            "2024-12-31": 2070477.0,
            "2023-12-31": 971751.0
          },
          "is_total": false
        },
        {
          "label_raw": "Profit for the year",
          "key": "profit_for_the_year_attributable",
          "values": {
            "2024-12-31": 15485117.0,
            "2023-12-31": 12258751.0
          },
          "is_total": true
        },
        {
          "label_raw": "Basic and diluted earnings per share (Fils)",
          "key": "basic_and_diluted_earnings_per_share_fils",
          "values": {
            "2024-12-31": 13.84,
            "2023-12-31": 11.68
          },
          "is_total": false
        }
      ]
    },
    "balance_sheet": {
      "statement_type": "balance_sheet",
      "currency": "KD",
      "unit_scale": 1,
      "periods": [
        {
          "label": "2024-12-31",
          "col_name": "2024"
        },
        {
          "label": "2023-12-31",
          "col_name": "2023"
        }
      ],
      "items": [
        {
          "label_raw": "Cash and cash equivalents",
          "key": "cash_and_cash_equivalents",
          "values": {
            "2024-12-31": 12356006.0,
            "2023-12-31": 6168176.0
          },
          "is_total": false
        },
        {
          "label_raw": "Financial assets at fair value through profit or loss",
          "key": "financial_assets_at_fair_value_through_profit_or_loss",
          "values": {
            "2024-12-31": 17836377.0,
            "2023-12-31": 10958486.0
          },
          "is_total": false
        },
        {
          "label_raw": "Accounts receivable and other assets",
          "key": "accounts_receivable_and_other_assets",
          "values": {
            "2024-12-31": 15370470.0,
            "2023-12-31": 22103820.0
          },
          "is_total": false
        },
        {
          "label_raw": "Due from related parties",
          "key": "due_from_related_parties",
          "values": {
            "2024-12-31": 13524005.0,
            "2023-12-31": 10312323.0
          },
          "is_total": false
        },
        {
          "label_raw": "Trading properties",
          "key": "trading_properties",
          "values": {
            "2024-12-31": 37182589.0,
            "2023-12-31": 8163775.0
          },
          "is_total": false
        },
        {
          "label_raw": "Investments in associates",
          "key": "investments_in_associates",
          "values": {
            "2024-12-31": 11424380.0,
            "2023-12-31": 13453616.0
          },
          "is_total": false
        },
        {
          "label_raw": "Financial assets at fair value through other comprehensive income",
          "key": "financial_assets_at_fair_value_through_other_comprehensive_income",
          "values": {
            "2024-12-31": 83073600.0,
            "2023-12-31": 52785580.0
          },
          "is_total": false
        },
        {
          "label_raw": "Investment in a subsidiary",
          "key": "investment_in_a_subsidiary",
          "values": {
            "2024-12-31": 1051102.0,
            "2023-12-31": null
          },
          "is_total": false
        },
        {
          "label_raw": "Properties under development",
          "key": "properties_under_development",
          "values": {
            "2024-12-31": 2835828.0,
            "2023-12-31": 7867584.0
          },
          "is_total": false
        },
        {
          "label_raw": "Investment properties",
          "key": "investment_properties",
          "values": {
            "2024-12-31": 202950859.0,
            "2023-12-31": 253707881.0
          },
          "is_total": false
        },
        {
          "label_raw": "Property and equipment",
          "key": "property_and_equipment",
          "values": {
            "2024-12-31": 2898014.0,
            "2023-12-31": 2407119.0
          },
          "is_total": false
        },
        {
          "label_raw": "Total assets",
          "key": "total_assets",
          "values": {
            "2024-12-31": 460912207.0,
            "2023-12-31": 393401360.0
          },
          "is_total": true
        },
        {
          "label_raw": "Bank overdrafts",
          "key": "bank_overdrafts",
          "values": {
            "2024-12-31": 5181424.0,
            "2023-12-31": 3561368.0
          },
          "is_total": false
        },
        {
          "label_raw": "Accounts payable and other liabilities",
          "key": "accounts_payable_and_other_liabilities",
          "values": {
            "2024-12-31": 21928048.0,
            "2023-12-31": 18535468.0
          },
          "is_total": false
        },
        {
          "label_raw": "Lease liabilities",
          "key": "lease_liabilities",
          "values": {
            "2024-12-31": 2232000.0,
            "2023-12-31": 2000000.0
          },
          "is_total": false
        },
        {
          "label_raw": "Borrowings",
          "key": "borrowings",
          "values": {
            "2024-12-31": 223347579.0,
            "2023-12-31": 199051069.0
          },
          "is_total": false
        },
        {
          "label_raw": "Due to related parties",
          "key": "due_to_related_parties",
          "values": {
            "2024-12-31": 5671040.0,
            "2023-12-31": 5734560.0
          },
          "is_total": false
        },
        {
          "label_raw": "Provision for employees' end of service benefits",
          "key": "provision_for_employees_end_of_service_benefits",
          "values": {
            "2024-12-31": 1141381.0,
            "2023-12-31": 1002916.0
          },
          "is_total": false
        },
        {
          "label_raw": "Total liabilities",
          "key": "total_liabilities",
          "values": {
            "2024-12-31": 265532272.0,
            "2023-12-31": 235725381.0
          },
          "is_total": true
        },
        {
          "label_raw": "Share capital",
          "key": "share_capital",
          "values": {
            "2024-12-31": 100420696.0,
            "2023-12-31": 94736506.0
          },
          "is_total": false
        },
        {
          "label_raw": "Share premium",
          "key": "share_premium",
          "values": {
            "2024-12-31": 3425191.0,
            "2023-12-31": 3425191.0
          },
          "is_total": false
        },
        {
          "label_raw": "Treasury shares",
          "key": "treasury_shares",
          "values": {
            "2024-12-31": -7135682.0,
            "2023-12-31": -5171096.0
          },
          "is_total": false
        },
        {
          "label_raw": "Statutory and voluntary reserves",
          "key": "statutory_and_voluntary_reserves",
          "values": {
            "2024-12-31": 29725313.0,
            "2023-12-31": 28981519.0
          },
          "is_total": false
        },
        {
          "label_raw": "Other components of equity",
          "key": "other_components_of_equity",
          "values": {
            "2024-12-31": 25663770.0,
            "2023-12-31": 1798379.0
          },
          "is_total": false
        },
        {
          "label_raw": "Retained earnings",
          "key": "retained_earnings",
          "values": {
            "2024-12-31": 26978681.0,
            "2023-12-31": 24402046.0
          },
          "is_total": false
        },
        {
          "label_raw": "Total equity attributable to owners of the Parent Company",
          "key": "total_equity_attributable_to_owners_of_the_parent_company",
          "values": {
            "2024-12-31": 178077969.0,
            "2023-12-31": 148072545.0
          },
          "is_total": true
        },
        {
          "label_raw": "Non-controlling interests",
          "key": "non_controlling_interests_equity",
          "values": {
            "2024-12-31": 16301960.0,
            "2023-12-31": 11603434.0
          },
          "is_total": false
        },
        {
          "label_raw": "Total equity",
          "key": "total_equity",
          "values": {
            "2024-12-31": 195379929.0,
            "2023-12-31": 157675979.0
          },
          "is_total": true
        },
        {
          "label_raw": "Total liabilities and equity",
          "key": "total_liabilities_and_equity",
          "values": {
            "2024-12-31": 460912207.0,
            "2023-12-31": 393401360.0
          },
          "is_total": true
        }
      ]
    },
    "equity_statement": {
      "statement_type": "equity_statement",
      "currency": "KD",
      "unit_scale": 1,
      "periods": [
        {
          "label": "2024-12-31",
          "col_name": "2024"
        },
        {
          "label": "2023-12-31",
          "col_name": "2023"
        }
      ],
      "items": [
        {
          "label_raw": "Balance at 1 January",
          "key": "balance_at_1_january",
          "values": {},
          "is_total": false
        }
      ]
    },
    "cash_flow": {
      "statement_type": "cash_flow",
      "currency": "KWD",
      "unit_scale": 1,
      "periods": [
        {
          "label": "2024-12-31",
          "col_name": "2024"
        },
        {
          "label": "2023-12-31",
          "col_name": "2023"
        }
      ],
      "items": [
        {
          "label_raw": "Profit for the year",
          "key": "profit_for_the_year",
          "values": {
            "2024-12-31": 15485117.0,
            "2023-12-31": 12258751.0
          },
          "is_total": false
        },
        {
          "label_raw": "Depreciation",
          "key": "depreciation",
          "values": {
            "2024-12-31": 749687.0,
            "2023-12-31": 226241.0
          },
          "is_total": false
        },
        {
          "label_raw": "Finance costs",
          "key": "finance_costs",
          "values": {
            "2024-12-31": 12890139.0,
            "2023-12-31": 10924254.0
          },
          "is_total": false
        },
        {
          "label_raw": "Gain on fair value of investment properties",
          "key": "gain_on_fair_value_of_investment_properties",
          "values": {
            "2024-12-31": -9475662.0,
            "2023-12-31": -6401328.0
          },
          "is_total": false
        },
        {
          "label_raw": "Gain on fair value of properties under development",
          "key": "gain_on_fair_value_of_properties_under_development",
          "values": {
            "2024-12-31": null,
            "2023-12-31": -4958263.0
          },
          "is_total": false
        },
        {
          "label_raw": "Share of results of associates",
          "key": "share_of_results_of_associates",
          "values": {
            "2024-12-31": -55683.0,
            "2023-12-31": -2008103.0
          },
          "is_total": false
        },
        {
          "label_raw": "Gain on disposal of associate",
          "key": "gain_on_disposal_of_associate",
          "values": {
            "2024-12-31": 2029457.0,
            "2023-12-31": 120000.0
          },
          "is_total": false
        },
        {
          "label_raw": "Change in fair value of financial assets at FVTPL",
          "key": "change_in_fair_value_of_financial_assets_at_fvtpl",
          "values": {
            "2024-12-31": -2485385.0,
            "2023-12-31": -758835.0
          },
          "is_total": false
        },
        {
          "label_raw": "Loss on sale of financial assets at FVTPL",
          "key": "loss_on_sale_of_financial_assets_at_fvtpl",
          "values": {
            "2024-12-31": 71738.0,
            "2023-12-31": 1600.0
          },
          "is_total": false
        },
        {
          "label_raw": "Provision charge for doubtful debts",
          "key": "provision_charge_for_doubtful_debts",
          "values": {
            "2024-12-31": null,
            "2023-12-31": 150927.0
          },
          "is_total": false
        },
        {
          "label_raw": "Dividend income",
          "key": "dividend_income",
          "values": {
            "2024-12-31": -375626.0,
            "2023-12-31": -362354.0
          },
          "is_total": false
        },
        {
          "label_raw": "Provision charge for employees' end of service benefits",
          "key": "provision_charge_for_employees_end_of_service_benefits",
          "values": {
            "2024-12-31": 234848.0,
            "2023-12-31": 35408.0
          },
          "is_total": false
        },
        {
          "label_raw": "Accounts receivable and other assets",
          "key": "accounts_receivable_and_other_assets",
          "values": {
            "2024-12-31": 2571948.0,
            "2023-12-31": -4791779.0
          },
          "is_total": false
        },
        {
          "label_raw": "Due from related parties",
          "key": "due_from_related_parties",
          "values": {
            "2024-12-31": 1787514.0,
            "2023-12-31": 2198194.0
          },
          "is_total": false
        },
        {
          "label_raw": "Accounts payable and other liabilities",
          "key": "accounts_payable_and_other_liabilities",
          "values": {
            "2024-12-31": 1523393.0,
            "2023-12-31": -1888882.0
          },
          "is_total": false
        },
        {
          "label_raw": "Due to related parties",
          "key": "due_to_related_parties",
          "values": {
            "2024-12-31": -42714.0,
            "2023-12-31": -2223267.0
          },
          "is_total": false
        },
        {
          "label_raw": "Employees' end of service benefits paid",
          "key": "employees_end_of_service_benefits_paid",
          "values": {
            "2024-12-31": -66094.0,
            "2023-12-31": -225405.0
          },
          "is_total": false
        },
        {
          "label_raw": "Net cash from operating activities",
          "key": "net_cash_from_operating_activities",
          "values": {
            "2024-12-31": 24595561.0,
            "2023-12-31": 6462893.0
          },
          "is_total": true
        },
        {
          "label_raw": "Purchase of property and equipment",
          "key": "purchase_of_property_and_equipment",
          "values": {
            "2024-12-31": -1240782.0,
            "2023-12-31": -1824051.0
          },
          "is_total": false
        },
        {
          "label_raw": "Additions to capital work in progress",
          "key": "additions_to_capital_work_in_progress",
          "values": {
            "2024-12-31": -1897922.0,
            "2023-12-31": 77835.0
          },
          "is_total": false
        },
        {
          "label_raw": "Additions to properties under development",
          "key": "additions_to_properties_under_development",
          "values": {
            "2024-12-31": -2780130.0,
            "2023-12-31": -2053874.0
          },
          "is_total": false
        },
        {
          "label_raw": "Additions to investment properties",
          "key": "additions_to_investment_properties",
          "values": {
            "2024-12-31": -2552306.0,
            "2023-12-31": -1043267.0
          },
          "is_total": false
        },
        {
          "label_raw": "Additions to trading properties",
          "key": "additions_to_trading_properties",
          "values": {
            "2024-12-31": null,
            "2023-12-31": 164699.0
          },
          "is_total": false
        }
      ]
    }
  },
  "validations": [
    {
      "statement_type": "balance_sheet",
      "rule_name": "assets_eq_liab_plus_equity",
      "expected": 393401360.0,
      "actual": 393401360.0,
      "diff": 0.0,
      "passed": true,
      "note": "period=2023-12-31 diff=0 (0.00%)"
    },
    {
      "statement_type": "balance_sheet",
      "rule_name": "assets_eq_liab_plus_equity",
      "expected": 460912201.0,
      "actual": 460912207.0,
      "diff": 6.0,
      "passed": true,
      "note": "period=2024-12-31 diff=6 (0.00%)"
    }
  ],
  "page_types": {
    "0": "income_statement",
    "1": "balance_sheet",
    "2": "equity_statement",
    "3": "equity_statement",
    "4": "cash_flow",
    "5": "cash_flow"
  },
  "page_hashes": {
    "0": "ce06eeaa3112a9ec",
    "1": "7d9f7af579eed40e",
    "2": "7e6c4b76eee3c3dd",
    "3": "e59beb230560b493",
    "4": "dd1fddd71a16b4ca",
    "5": "d98ffb24dfa1becb"
  },
  "timings": {
    "render": 2.73,
    "batch_extract": 64.92,
    "fallback_extract": 30.54,
    "validate": 0.0,
    "persist": 1.01,
    "total": 100.26
  },
  "_from_cache": false
}